MANIFEST.in
setup.cfg
setup.py
bin/buckle
bin/buckle-_help-helper
bin/buckle-help
bin/buckle-init
bin/buckle-readme
bin/buckle-version
buckle/README.md
buckle/__init__.py
buckle/autocomplete.py
buckle/help_formatters.py
buckle/init.sh
buckle/message.py
buckle/ntp.py
buckle/path.py
buckle/system_clock.py
buckle/version.py
buckle.egg-info/PKG-INFO
buckle.egg-info/SOURCES.txt
buckle.egg-info/dependency_links.txt
buckle.egg-info/requires.txt
buckle.egg-info/top_level.txt
buckle/commands/__init__.py
buckle/commands/base.py
buckle/commands/help.py
buckle/commands/help_helper.py
buckle/commands/init.py
buckle/commands/readme.py
buckle/commands/version.py
tests/__init__.py
tests/conftest.py
tests/test_autocomplete.py
tests/test_help_formatters.py
tests/test_ntp.py
tests/test_path.py
tests/test_system_clock.py