Metadata-Version: 1.0
Name: buckle
Version: 0.1.0
Summary: Buckle: It ties your toolbelt together
Home-page: https://git.corp.nextdoor.com/Nextdoor/buckle
Author: Nextdoor
Author-email: eng@nextdoor.com
License: UNKNOWN
Platform: UNKNOWN
